GoplZh/README.md
GoplZh/__init__.py
GoplZh/__main__.py
GoplZh/file.epub
GoplZh/index.html
GoplZh/css/__init__.py
GoplZh/css/annotations.css
GoplZh/css/main.css
GoplZh/css/normalize.css
GoplZh/css/popup.css
GoplZh/font/__init__.py
GoplZh/font/fontello.eot
GoplZh/font/fontello.svg
GoplZh/font/fontello.ttf
GoplZh/font/fontello.woff
GoplZh/img/__init__.py
GoplZh/img/annotator-glyph-sprite.png
GoplZh/img/annotator-icon-sprite.png
GoplZh/img/apple-touch-icon.png
GoplZh/img/cancelfullscreen.png
GoplZh/img/close.png
GoplZh/img/fullscreen.png
GoplZh/img/loader.gif
GoplZh/img/menu-icon.png
GoplZh/img/save.png
GoplZh/img/saved.png
GoplZh/img/settings-s.png
GoplZh/img/settings.png
GoplZh/img/star.png
GoplZh/js/__init__.py
GoplZh/js/epub.js
GoplZh/js/epub.min.js
GoplZh/js/epub.min.map
GoplZh/js/hooks.min.js
GoplZh/js/hooks.min.map
GoplZh/js/reader.js
GoplZh/js/reader.js.map
GoplZh/js/reader.min.js
GoplZh/js/reader.min.map
GoplZh/js/hooks/__init__.py
GoplZh/js/hooks/extensions/__init__.py
GoplZh/js/hooks/extensions/highlight.js
GoplZh/js/libs/__init__.py
GoplZh/js/libs/jquery.min.js
GoplZh/js/libs/localforage.min.js
GoplZh/js/libs/screenfull.js
GoplZh/js/libs/screenfull.min.js
GoplZh/js/libs/zip.min.js
GoplZh/js/plugins/__init__.py
GoplZh/js/plugins/hypothesis.js
GoplZh/js/plugins/search.js
gopl_zh-2024.3.1.0.dist-info/METADATA
gopl_zh-2024.3.1.0.dist-info/WHEEL
gopl_zh-2024.3.1.0.dist-info/entry_points.txt
gopl_zh-2024.3.1.0.dist-info/top_level.txt
gopl_zh-2024.3.1.0.dist-info/RECORD
